LICENCE.txt
MANIFEST.in
README.rst
setup.py
micode/__init__.py
micode.py.egg-info/PKG-INFO
micode.py.egg-info/SOURCES.txt
micode.py.egg-info/dependency_links.txt
micode.py.egg-info/requires.txt
micode.py.egg-info/top_level.txt