Metadata-Version: 2.1
Name: micode.py
Version: 1.0.0
Summary: Moja biblioteka (Miki3oo5)
Home-page: 
Author: Miki3oo5
Author-email: mikolajzelazny5@gmail.com
License: MIT
Keywords: Miki3oo5
Platform: UNKNOWN
Classifier: Development Status :: 5 - Production/Stable
Classifier: Intended Audience :: Education
Classifier: Operating System :: Microsoft :: Windows :: Windows 10
Classifier: License :: OSI Approved :: MIT License
Classifier: Programming Language :: Python :: 3
License-File: LICENCE.txt
